j_crypto/__init__.py
j_crypto/creator.py
j_crypto/loader.py
j_crypto-0.1.data/scripts/j-crypto-create-pair
j_crypto-0.1.dist-info/METADATA
j_crypto-0.1.dist-info/WHEEL
j_crypto-0.1.dist-info/top_level.txt
j_crypto-0.1.dist-info/RECORD
