Metadata-Version: 2.1
Name: j-crypto
Version: 0.1
Summary: Helper fucntions to deal with RSA keys
Home-page: https://github.com/foothub/crypto-utils
Author: Acciaioli Valverde
Author-email: acci.valverde@gmail.com
License: UNKNOWN
Platform: UNKNOWN
Classifier: Programming Language :: Python :: 3.7
Classifier: License :: OSI Approved :: MIT License
Requires-Dist: pyjwt
Requires-Dist: cryptography
